jupyter_smart_on_fhir/__init__.py
jupyter_smart_on_fhir/auth.py
jupyter_smart_on_fhir/hub_service.py
jupyter_smart_on_fhir/server_extension.py
jupyter_smart_on_fhir-0.1.0a3.data/data/etc/jupyter/jupyter_server_config.d/jupyter-smart-on-fhir.json
jupyter_smart_on_fhir-0.1.0a3.dist-info/licenses/LICENSE
jupyter_smart_on_fhir-0.1.0a3.dist-info/METADATA
jupyter_smart_on_fhir-0.1.0a3.dist-info/WHEEL
jupyter_smart_on_fhir-0.1.0a3.dist-info/top_level.txt
jupyter_smart_on_fhir-0.1.0a3.dist-info/RECORD
