Metadata-Version: 2.4
Name: jupyter-smart-on-fhir
Version: 0.1.0a3
Summary: Jupyter Extension for SMART on FHIR launch
License-Expression: BSD-3-Clause
Project-URL: Homepage, https://github.com/jupyterhealth/jupyter-smart-on-fhir
Project-URL: Source, https://github.com/jupyterhealth/jupyter-smart-on-fhir
Project-URL: Tracker, https://github.com/jupyterhealth/jupyter-smart-on-fhir/issues
Keywords: Jupyter,JupyterHub,SMART,FHIR
Classifier: Development Status :: 1 - Planning
Classifier: Intended Audience :: Developers
Classifier: Intended Audience :: System Administrators
Classifier: Intended Audience :: Science/Research
Classifier: Programming Language :: Python
Classifier: Programming Language :: Python :: 3
Classifier: Framework :: Jupyter
Requires-Python: >=3.9
License-File: LICENSE
Requires-Dist: pyjwt
Requires-Dist: requests
Provides-Extra: test
Requires-Dist: pytest; extra == "test"
Requires-Dist: pytest-jupyter[server]; extra == "test"
Requires-Dist: jupyter-smart-on-fhir[hubservice,serverextension]; extra == "test"
Provides-Extra: hubservice
Requires-Dist: flask; extra == "hubservice"
Requires-Dist: jupyterhub; extra == "hubservice"
Provides-Extra: serverextension
Requires-Dist: jupyter-server; extra == "serverextension"
Requires-Dist: tornado; extra == "serverextension"
Dynamic: license-file
